wizard_prompt_cli/__init__.py
wizard_prompt_cli/cli.py
wizard_prompt_cli/inference.py
wizard_prompt_cli-0.5.0.dist-info/licenses/LICENSE
wizard_prompt_cli-0.5.0.dist-info/METADATA
wizard_prompt_cli-0.5.0.dist-info/WHEEL
wizard_prompt_cli-0.5.0.dist-info/entry_points.txt
wizard_prompt_cli-0.5.0.dist-info/top_level.txt
wizard_prompt_cli-0.5.0.dist-info/RECORD
