Metadata-Version: 2.4
Name: wizard-prompt-cli
Version: 0.5.0
Summary: A CLI tool for building and running magical LLM prompts
Author-email: Scott Pierce <ddrscott@gmail.com>
Requires-Python: >=3.11
License-File: LICENSE
Requires-Dist: openai>=1.20.0
Requires-Dist: click>=8.1.8
Requires-Dist: pyyaml>=6.0.2
Requires-Dist: rich>=13.9.4
Requires-Dist: tiktoken>=0.9.0
Requires-Dist: litellm>=1.66.1
Provides-Extra: dev
Requires-Dist: pytest>=7.3.1; extra == "dev"
Requires-Dist: pytest-mock>=3.10.0; extra == "dev"
Dynamic: license-file
